design.sv
module counter (
    input logic [4:0] data,
    input logic load,
    input logic enable,
    input logic clk,
    input logic rst_,
    output logic [4:0] count
);

    always_ff @(posedge clk or negedge rst_) begin
        if (!rst_) begin
            count <= 5'b0;
        end else if (load) begin
            count <= data;
        end else if (enable) begin
            count <= count + 1;
        end
    end

endmodule

testbench.sv
`timescale 1ns/1ps

module counter_test;

    logic [4:0] data;
    logic load;
    logic enable;
    logic clk;
    logic rst_;
    logic [4:0] count;

    // Instantiate the counter
    counter uut (
        .data(data),
        .load(load),
        .enable(enable),
        .clk(clk),
        .rst_(rst_),
        .count(count)
    );

    // Clock generation
    initial begin
        clk = 0;
        forever #5 clk = ~clk;
    end

    // Stimulus
    initial begin
        // Initialize signals
        rst_ = 1;
        load = 0;
        enable = 0;
        data = 5'b0;

        // Apply reset
        rst_ = 0;
        #10;
        rst_ = 1;
        #10;

        // Load data
        load = 1;
        data = 5'b10101;
        #10;
        load = 0;

        // Enable counting
        enable = 1;
        #50;

        // Disable counting
        enable = 0;
        #10;

        // Load new data
        load = 1;
        data = 5'b01010;
        #10;
        load = 0;

        // Enable counting
        enable = 1;
        #50;

        // End simulation
        $stop;
    end

    // Monitor signals
    initial begin
        $monitor("time=%0t clk=%b rst_=%b load=%b enable=%b data=%b count=%b", 
                  $time, clk, rst_, load, enable, data, count);
    end

    // Dump waveform
    initial begin
        $dumpfile("dump.vcd");
        $dumpvars(0, counter_test);
    end

endmodule

dump.vcd
$date
    Aug  7, 2024  00:46:09
$end
$version
    TOOL:	xmsim	23.09-s001
$end
$timescale
    1 ps
$end

$scope module counter_test $end
$var reg       5 !    data [4:0] $end
$var reg       1 "    load $end
$var reg       1 #    enable $end
$var reg       1 $    clk $end
$var reg       1 %    rst_ $end
$var reg       5 &    count [4:0] $end

$scope module uut $end
$var wire      5 '    data [4:0] $end
$var wire      1 (    load  $end
$var wire      1 )    enable  $end
$var wire      1 *    clk  $end
$var wire      1 +    rst_  $end
$var reg       5 ,    count [4:0] $end
$upscope $end

$upscope $end

$enddefinitions $end
$dumpvars
b0 !
0"
0#
0$
0%
b0 &
b0 '
0(
0)
0*
0+
b0 ,
$end
#5000
1$
1*
#10000
1%
0$
0*
1+
#15000
1$
1*
#20000
1"
b10101 !
0$
0*
b10101 '
1(
#25000
1$
1*
b10101 ,
b10101 &
#30000
0"
1#
0$
0*
1)
0(
#35000
1$
1*
b10110 ,
b10110 &
#40000
0$
0*
#45000
1$
1*
b10111 ,
b10111 &
#50000
0$
0*
#55000
1$
1*
b11000 ,
b11000 &
#60000
0$
0*
#65000
1$
1*
b11001 ,
b11001 &
#70000
0$
0*
#75000
1$
1*
b11010 ,
b11010 &
#80000
0#
0$
0*
0)
#85000
1$
1*
#90000
1"
b1010 !
0$
0*
b1010 '
1(
#95000
1$
1*
b1010 ,
b1010 &
#100000
0"
1#
0$
0*
1)
0(
#105000
1$
1*
b1011 ,
b1011 &
#110000
0$
0*
#115000
1$
1*
b1100 ,
b1100 &
#120000
0$
0*
#125000
1$
1*
b1101 ,
b1101 &
#130000
0$
0*
#135000
1$
1*
b1110 ,
b1110 &
#140000
0$
0*
#145000
1$
1*
b1111 ,
b1111 &
